vfo/Get_Rendering.py
vfo/__init__.py
vfo/classTags.py
vfo/internal_database_functions.py
vfo/internal_plotting_functions.py
vfo/live_model_view.py
vfo/vfo.py
vfo-0.0.19.dist-info/LICENSE
vfo-0.0.19.dist-info/METADATA
vfo-0.0.19.dist-info/WHEEL
vfo-0.0.19.dist-info/top_level.txt
vfo-0.0.19.dist-info/RECORD
