Metadata-Version: 2.1
Name: vfo
Version: 0.0.19
Summary: A package for visualization of OpenSees models.
Home-page: https://github.com/u-anurag/vfo
Author: anurag upadhyay
Author-email: iitg.anurag@gmail.com
Classifier: Programming Language :: Python :: 3
Classifier: License :: OSI Approved :: MIT License
Classifier: Operating System :: OS Independent
Requires-Python: >=3.10
License-File: LICENSE
Requires-Dist: numpy
Requires-Dist: matplotlib
Requires-Dist: pyvista
Requires-Dist: imageio
Requires-Dist: imageio[ffmpeg]
Requires-Dist: imageio[pyav]
Requires-Dist: ipywidgets
Requires-Dist: trame
Requires-Dist: trame-vtk
Requires-Dist: trame-vuetify
Requires-Dist: trame-plotly
